{"url": "http://dx.doi.org/10.1353/dph.2019.0016", "identifier": {"string_id": "10.1353/dph.2019.0016", "id_scheme": "DOI"}, "abstract": "This essay synthesizes the perspectives of eleven participants in a colloquium that brought together experts in medieval language and culture, second-language acquisition, and video game production to assess the use of three-dimensional (3D) immersive environments for learning about inaccessible or lost cultures. We suggest that technology offers a unique method for experiencing the past; and when harnessed effectively, immersive environments can increase empathy and learning while appealing to a new generation of students.", "article_title": "Revisioning the Global Middle Ages: Immersive Environments for Teaching Medieval Languages and Culture", "authors": [{"given": "Lynn", "family": "Ramey", "affiliation": [{"original_name": "Vanderbilt University", "normalized_name": "Vanderbilt University", "country": "United States", "identifiers": {"ror": "https://ror.org/02vm5rt34", "GRID": "grid.152326.1"}}]}, {"given": "David", "family": "Neville", "affiliation": [{"original_name": "Grinnell College", "normalized_name": "Grinnell College", "country": "United States", "identifiers": {"ror": "https://ror.org/04tmmky42", "GRID": "grid.256592.f"}}]}, {"given": "Sahar", "family": "Amer", "affiliation": [{"original_name": "University of Sydney", "normalized_name": "University of Sydney", "country": "Australia", "identifiers": {"ror": "https://ror.org/0384j8v12", "GRID": "grid.1013.3"}}, {"original_name": "Ruhr-Universität Bochum", "normalized_name": "University Hospitals of the Ruhr-University of Bochum", "country": "Germany", "identifiers": {"ror": "https://ror.org/03zcpvf19", "GRID": "grid.411091.c"}}]}, {"given": "Jonathan", "family": "deHaan", "affiliation": [{"original_name": "University of Shizuoka", "normalized_name": "University of Shizuoka", "country": "Japan", "identifiers": {"ror": "https://ror.org/04rvw0k47", "GRID": "grid.469280.1"}}]}, {"given": "Maxime", "family": "Durand", "affiliation": [{"original_name": "Ubisoft Montreal", "normalized_name": null, "country": null, "identifiers": {"ror": null, "GRID": null}}]}, {"given": "Brandon", "family": "Essary", "affiliation": [{"original_name": "Elon University", "normalized_name": "Elon University", "country": "United States", "identifiers": {"ror": "https://ror.org/01szgyb91", "GRID": "grid.255496.9"}}]}, {"given": "Rob", "family": "Howland", "affiliation": [{"original_name": "Three Flip Studios", "normalized_name": null, "country": null, "identifiers": {"ror": null, "GRID": null}}]}, {"given": "Mubbasir", "family": "Kapadia", "affiliation": [{"original_name": "Rutgers University", "normalized_name": "Rutgers, The State University of New Jersey", "country": "United States", "identifiers": {"ror": "https://ror.org/05vt9qd57", "GRID": "grid.430387.b"}}]}, {"given": "Felix", "family": "Kronenberg", "affiliation": [{"original_name": "Michigan State University", "normalized_name": "Michigan State University", "country": "United States", "identifiers": {"ror": "https://ror.org/05hs6h993", "GRID": "grid.17088.36"}}]}, {"given": "Brett E.", "family": "Shelton", "affiliation": [{"original_name": "Boise State University", "normalized_name": "Boise State University", "country": "United States", "identifiers": {"ror": "https://ror.org/02e3zdp86", "GRID": "grid.184764.8"}}]}, {"given": "Barbara", "family": "Vance", "affiliation": [{"original_name": "Indiana University", "normalized_name": "Indiana University", "country": "United States", "identifiers": {"ror": "https://ror.org/01kg8sb98", "GRID": "grid.257410.5"}}]}], "publisher": "Johns Hopkins University Press", "date": "2019", "keywords": null, "journal_title": "Digital Philology: A Journal of Medieval Cultures", "volume": "8", "issue": "1", "ISSN": [{"value": "2162-9552", "type": "electronic"}]}