{"url": "http://computerphilologie.digital-humanities.de/jg04/buettner/buettner.html", "identifier": {"string_id": null, "id_scheme": null}, "abstract": "The integration of the medium Internet into the traditional system of scientific communication is still in a transitional process. New ways of knowledge transfer, different forms of communication as well as information retrieval are yet to be tested. Depending on the different communication cultures among academic disciplines, the focus of interest might vary and should be adjusted to a variety of needs and individual preferences. For the field of historical science, the example of the internet-project historicum.net and its predecessor Server Frühe Neuzeit may illustrate the search for appropriate concepts as well as the problems that arise.", "article_title": "ERFAHRUNGEN MIT DER VIRTUELLEN WISSENSCHAFT. VOM SERVER FRÜHE NEUZEIT ZUM HISTORICUM.NET", "authors": [{"given": "Sabine", "family": "Büttner", "affiliation": [{"original_name": "Universität zu Köln", "normalized_name": "University of Cologne", "country": "Germany", "identifiers": {"ror": "https://ror.org/00rcxh774", "GRID": "grid.6190.e"}}]}], "publisher": null, "date": "2004", "keywords": null, "journal_title": "Jahrbuch für Computerphilologie", "volume": null, "issue": null, "ISSN": [{"value": null, "type": null}]}