[
    {
        "url": "http://dx.doi.org/10.1007/s42803-019-00025-5",
        "identifier": {
            "string_id": "10.1007/s42803-019-00025-5",
            "id_scheme": "DOI"
        },
        "abstract": [],
        "article_title": "The ‘assertive edition’",
        "authors": [
            {
                "given": "Georg",
                "family": "Vogeler",
                "sequence": "first",
                "affiliation": []
            }
        ],
        "publisher": "Springer Science and Business Media LLC",
        "date": "2019-05-11T15:36:36Z",
        "keywords": [],
        "journal_title": "International Journal of Digital Humanities",
        "volume": "1",
        "issue": "2",
        "ISSN": [
            {
                "value": "2524-7832",
                "type": "print"
            },
            {
                "value": "2524-7840",
                "type": "electronic"
            }
        ]
    },
    {
        "url": "http://dx.doi.org/10.1007/s42803-019-00023-7",
        "identifier": {
            "string_id": "10.1007/s42803-019-00023-7",
            "id_scheme": "DOI"
        },
        "abstract": [],
        "article_title": "Exercises in modelling: textual variants",
        "authors": [
            {
                "given": "Elena",
                "family": "Spadini",
                "sequence": "first",
                "affiliation": []
            }
        ],
        "publisher": "Springer Science and Business Media LLC",
        "date": "2019-05-30T05:04:40Z",
        "keywords": [],
        "journal_title": "International Journal of Digital Humanities",
        "volume": "1",
        "issue": "2",
        "ISSN": [
            {
                "value": "2524-7832",
                "type": "print"
            },
            {
                "value": "2524-7840",
                "type": "electronic"
            }
        ]
    },
    {
        "url": "http://dx.doi.org/10.1007/s42803-019-00021-9",
        "identifier": {
            "string_id": "10.1007/s42803-019-00021-9",
            "id_scheme": "DOI"
        },
        "abstract": [],
        "article_title": "The Charles Harpur Critical Archive",
        "authors": [
            {
                "given": "Desmond",
                "family": "Schmidt",
                "sequence": "first",
                "affiliation": []
            },
            {
                "given": "Paul",
                "family": "Eggert",
                "sequence": "additional",
                "affiliation": []
            }
        ],
        "publisher": "Springer Science and Business Media LLC",
        "date": "2019-05-16T01:09:29Z",
        "keywords": [],
        "journal_title": "International Journal of Digital Humanities",
        "volume": "1",
        "issue": "2",
        "ISSN": [
            {
                "value": "2524-7832",
                "type": "print"
            },
            {
                "value": "2524-7840",
                "type": "electronic"
            }
        ]
    },
    {
        "url": "http://dx.doi.org/10.1007/s42803-019-00018-4",
        "identifier": {
            "string_id": "10.1007/s42803-019-00018-4",
            "id_scheme": "DOI"
        },
        "abstract": [],
        "article_title": "On edited archives and archived editions",
        "authors": [
            {
                "given": "Wout",
                "family": "Dillen",
                "sequence": "first",
                "affiliation": []
            }
        ],
        "publisher": "Springer Science and Business Media LLC",
        "date": "2019-04-29T05:03:07Z",
        "keywords": [],
        "journal_title": "International Journal of Digital Humanities",
        "volume": "1",
        "issue": "2",
        "ISSN": [
            {
                "value": "2524-7832",
                "type": "print"
            },
            {
                "value": "2524-7840",
                "type": "electronic"
            }
        ]
    },
    {
        "url": "http://dx.doi.org/10.1007/s42803-019-00014-8",
        "identifier": {
            "string_id": "10.1007/s42803-019-00014-8",
            "id_scheme": "DOI"
        },
        "abstract": [],
        "article_title": "Editing social media: the case of online book discussion",
        "authors": [
            {
                "given": "Peter",
                "family": "Boot",
                "sequence": "first",
                "affiliation": []
            }
        ],
        "publisher": "Springer Science and Business Media LLC",
        "date": "2019-05-23T05:17:07Z",
        "keywords": [],
        "journal_title": "International Journal of Digital Humanities",
        "volume": "1",
        "issue": "2",
        "ISSN": [
            {
                "value": "2524-7832",
                "type": "print"
            },
            {
                "value": "2524-7840",
                "type": "electronic"
            }
        ]
    },
    {
        "url": "http://dx.doi.org/10.1007/s42803-019-00013-9",
        "identifier": {
            "string_id": "10.1007/s42803-019-00013-9",
            "id_scheme": "DOI"
        },
        "abstract": [],
        "article_title": "Tracking the evolution of translated documents: revisions, languages and contaminations",
        "authors": [
            {
                "given": "Gioele",
                "family": "Barabucci",
                "sequence": "first",
                "affiliation": []
            }
        ],
        "publisher": "Springer Science and Business Media LLC",
        "date": "2019-06-28T16:03:07Z",
        "keywords": [],
        "journal_title": "International Journal of Digital Humanities",
        "volume": "1",
        "issue": "2",
        "ISSN": [
            {
                "value": "2524-7832",
                "type": "print"
            },
            {
                "value": "2524-7840",
                "type": "electronic"
            }
        ]
    },
    {
        "url": "http://dx.doi.org/10.1007/s42803-019-00024-6",
        "identifier": {
            "string_id": "10.1007/s42803-019-00024-6",
            "id_scheme": "DOI"
        },
        "abstract": [],
        "article_title": "Textuality in 3D: three-dimensional (re)constructions as digital scholarly editions",
        "authors": [
            {
                "given": "Susan",
                "family": "Schreibman",
                "sequence": "first",
                "affiliation": []
            },
            {
                "given": "Costas",
                "family": "Papadopoulos",
                "sequence": "additional",
                "affiliation": []
            }
        ],
        "publisher": "Springer Science and Business Media LLC",
        "date": "2019-05-14T13:16:32Z",
        "keywords": [],
        "journal_title": "International Journal of Digital Humanities",
        "volume": "1",
        "issue": "2",
        "ISSN": [
            {
                "value": "2524-7832",
                "type": "print"
            },
            {
                "value": "2524-7840",
                "type": "electronic"
            }
        ]
    },
    {
        "url": "http://dx.doi.org/10.1007/s42803-019-00019-3",
        "identifier": {
            "string_id": "10.1007/s42803-019-00019-3",
            "id_scheme": "DOI"
        },
        "abstract": [],
        "article_title": "What future for digital scholarly editions? From Haute Couture to Prêt-à-Porter",
        "authors": [
            {
                "given": "Elena",
                "family": "Pierazzo",
                "sequence": "first",
                "affiliation": []
            }
        ],
        "publisher": "Springer Science and Business Media LLC",
        "date": "2019-05-01T08:02:28Z",
        "keywords": [],
        "journal_title": "International Journal of Digital Humanities",
        "volume": "1",
        "issue": "2",
        "ISSN": [
            {
                "value": "2524-7832",
                "type": "print"
            },
            {
                "value": "2524-7840",
                "type": "electronic"
            }
        ]
    },
    {
        "url": "http://dx.doi.org/10.1007/s42803-019-00017-5",
        "identifier": {
            "string_id": "10.1007/s42803-019-00017-5",
            "id_scheme": "DOI"
        },
        "abstract": [],
        "article_title": "Copies and facsimiles",
        "authors": [
            {
                "given": "Mats",
                "family": "Dahlström",
                "sequence": "first",
                "affiliation": []
            }
        ],
        "publisher": "Springer Science and Business Media LLC",
        "date": "2019-05-08T00:02:57Z",
        "keywords": [],
        "journal_title": "International Journal of Digital Humanities",
        "volume": "1",
        "issue": "2",
        "ISSN": [
            {
                "value": "2524-7832",
                "type": "print"
            },
            {
                "value": "2524-7840",
                "type": "electronic"
            }
        ]
    },
    {
        "url": "http://dx.doi.org/10.1007/s42803-019-00016-6",
        "identifier": {
            "string_id": "10.1007/s42803-019-00016-6",
            "id_scheme": "DOI"
        },
        "abstract": [],
        "article_title": "Opening the book: data models and distractions in digital scholarly editing",
        "authors": [
            {
                "given": "James",
                "family": "Cummings",
                "sequence": "first",
                "affiliation": []
            }
        ],
        "publisher": "Springer Science and Business Media LLC",
        "date": "2019-05-16T05:50:00Z",
        "keywords": [],
        "journal_title": "International Journal of Digital Humanities",
        "volume": "1",
        "issue": "2",
        "ISSN": [
            {
                "value": "2524-7832",
                "type": "print"
            },
            {
                "value": "2524-7840",
                "type": "electronic"
            }
        ]
    },
    {
        "url": "http://dx.doi.org/10.1007/s42803-019-00015-7",
        "identifier": {
            "string_id": "10.1007/s42803-019-00015-7",
            "id_scheme": "DOI"
        },
        "abstract": [],
        "article_title": "Charles Chesnutt and the case for hybrid editing",
        "authors": [
            {
                "given": "Stephanie P.",
                "family": "Browner",
                "sequence": "first",
                "affiliation": []
            },
            {
                "given": "Kenneth M.",
                "family": "Price",
                "sequence": "additional",
                "affiliation": []
            }
        ],
        "publisher": "Springer Science and Business Media LLC",
        "date": "2019-05-03T20:04:44Z",
        "keywords": [],
        "journal_title": "International Journal of Digital Humanities",
        "volume": "1",
        "issue": "2",
        "ISSN": [
            {
                "value": "2524-7832",
                "type": "print"
            },
            {
                "value": "2524-7840",
                "type": "electronic"
            }
        ]
    },
    {
        "url": "http://dx.doi.org/10.1007/s42803-019-00012-w",
        "identifier": {
            "string_id": "10.1007/s42803-019-00012-w",
            "id_scheme": "DOI"
        },
        "abstract": [],
        "article_title": "From graveyard to graph",
        "authors": [
            {
                "given": "Elli",
                "family": "Bleeker",
                "sequence": "first",
                "affiliation": []
            },
            {
                "given": "Bram",
                "family": "Buitendijk",
                "sequence": "additional",
                "affiliation": []
            },
            {
                "given": "Ronald",
                "family": "Haentjens Dekker",
                "sequence": "additional",
                "affiliation": []
            }
        ],
        "publisher": "Springer Science and Business Media LLC",
        "date": "2019-06-19T17:02:42Z",
        "keywords": [],
        "journal_title": "International Journal of Digital Humanities",
        "volume": "1",
        "issue": "2",
        "ISSN": [
            {
                "value": "2524-7832",
                "type": "print"
            },
            {
                "value": "2524-7840",
                "type": "electronic"
            }
        ]
    },
    {
        "url": "http://dx.doi.org/10.1007/s42803-019-00020-w",
        "identifier": {
            "string_id": "10.1007/s42803-019-00020-w",
            "id_scheme": "DOI"
        },
        "abstract": [],
        "article_title": "Artificial imagination, imagine: new developments in digital scholarly editing",
        "authors": [
            {
                "given": "Dirk",
                "family": "Van Hulle",
                "sequence": "first",
                "affiliation": []
            }
        ],
        "publisher": "Springer Science and Business Media LLC",
        "date": "2019-04-25T22:04:13Z",
        "keywords": [],
        "journal_title": "International Journal of Digital Humanities",
        "volume": "1",
        "issue": "2",
        "ISSN": [
            {
                "value": "2524-7832",
                "type": "print"
            },
            {
                "value": "2524-7840",
                "type": "electronic"
            }
        ]
    },
    {
        "url": "http://dx.doi.org/10.1007/s42803-019-00010-y",
        "identifier": {
            "string_id": "10.1007/s42803-019-00010-y",
            "id_scheme": "DOI"
        },
        "abstract": [],
        "article_title": "Web 25. Histories from the first 25 years of the world wide web",
        "authors": [
            {
                "given": "Peter",
                "family": "Mechant",
                "sequence": "first",
                "affiliation": []
            }
        ],
        "publisher": "Springer Science and Business Media LLC",
        "date": "2019-02-25T16:25:06Z",
        "keywords": [],
        "journal_title": "International Journal of Digital Humanities",
        "volume": "1",
        "issue": "1",
        "ISSN": [
            {
                "value": "2524-7832",
                "type": "print"
            },
            {
                "value": "2524-7840",
                "type": "electronic"
            }
        ]
    },
    {
        "url": "http://dx.doi.org/10.1007/s42803-019-00008-6",
        "identifier": {
            "string_id": "10.1007/s42803-019-00008-6",
            "id_scheme": "DOI"
        },
        "abstract": [],
        "article_title": "A landscape of data – working with digital resources within and beyond DARIAH",
        "authors": [
            {
                "given": "Tibor",
                "family": "Kálmán",
                "sequence": "first",
                "affiliation": []
            },
            {
                "given": "Matej",
                "family": "Ďurčo",
                "sequence": "additional",
                "affiliation": []
            },
            {
                "given": "Frank",
                "family": "Fischer",
                "sequence": "additional",
                "affiliation": []
            },
            {
                "given": "Nicolas",
                "family": "Larrousse",
                "sequence": "additional",
                "affiliation": []
            },
            {
                "given": "Claudio",
                "family": "Leone",
                "sequence": "additional",
                "affiliation": []
            },
            {
                "given": "Karlheinz",
                "family": "Mörth",
                "sequence": "additional",
                "affiliation": []
            },
            {
                "given": "Carsten",
                "family": "Thiel",
                "sequence": "additional",
                "affiliation": []
            }
        ],
        "publisher": "Springer Science and Business Media LLC",
        "date": "2019-04-04T04:48:57Z",
        "keywords": [],
        "journal_title": "International Journal of Digital Humanities",
        "volume": "1",
        "issue": "1",
        "ISSN": [
            {
                "value": "2524-7832",
                "type": "print"
            },
            {
                "value": "2524-7840",
                "type": "electronic"
            }
        ]
    },
    {
        "url": "http://dx.doi.org/10.1007/s42803-019-00007-7",
        "identifier": {
            "string_id": "10.1007/s42803-019-00007-7",
            "id_scheme": "DOI"
        },
        "abstract": [],
        "article_title": "Web archives as a data resource for digital scholars",
        "authors": [
            {
                "given": "Eveline",
                "family": "Vlassenroot",
                "sequence": "first",
                "affiliation": []
            },
            {
                "given": "Sally",
                "family": "Chambers",
                "sequence": "additional",
                "affiliation": []
            },
            {
                "given": "Emmanuel",
                "family": "Di Pretoro",
                "sequence": "additional",
                "affiliation": []
            },
            {
                "given": "Friedel",
                "family": "Geeraert",
                "sequence": "additional",
                "affiliation": []
            },
            {
                "given": "Gerald",
                "family": "Haesendonck",
                "sequence": "additional",
                "affiliation": []
            },
            {
                "given": "Alejandra",
                "family": "Michel",
                "sequence": "additional",
                "affiliation": []
            },
            {
                "given": "Peter",
                "family": "Mechant",
                "sequence": "additional",
                "affiliation": []
            }
        ],
        "publisher": "Springer Science and Business Media LLC",
        "date": "2019-03-08T17:11:50Z",
        "keywords": [],
        "journal_title": "International Journal of Digital Humanities",
        "volume": "1",
        "issue": "1",
        "ISSN": [
            {
                "value": "2524-7832",
                "type": "print"
            },
            {
                "value": "2524-7840",
                "type": "electronic"
            }
        ]
    },
    {
        "url": "http://dx.doi.org/10.1007/s42803-019-00006-8",
        "identifier": {
            "string_id": "10.1007/s42803-019-00006-8",
            "id_scheme": "DOI"
        },
        "abstract": [],
        "article_title": "The invention and dissemination of the spacer gif: implications for the future of access and use of web archives",
        "authors": [
            {
                "given": "Trevor",
                "family": "Owens",
                "sequence": "first",
                "affiliation": []
            },
            {
                "given": "Grace Helen",
                "family": "Thomas",
                "sequence": "additional",
                "affiliation": []
            }
        ],
        "publisher": "Springer Science and Business Media LLC",
        "date": "2019-04-05T17:13:56Z",
        "keywords": [],
        "journal_title": "International Journal of Digital Humanities",
        "volume": "1",
        "issue": "1",
        "ISSN": [
            {
                "value": "2524-7832",
                "type": "print"
            },
            {
                "value": "2524-7840",
                "type": "electronic"
            }
        ]
    },
    {
        "url": "http://dx.doi.org/10.1007/s42803-019-00005-9",
        "identifier": {
            "string_id": "10.1007/s42803-019-00005-9",
            "id_scheme": "DOI"
        },
        "abstract": [],
        "article_title": "Anarchive as technique in the Media Archaeology Lab | building a one Laptop Per Child mesh network",
        "authors": [
            {
                "given": "libi",
                "family": "striegl",
                "sequence": "first",
                "affiliation": []
            },
            {
                "given": "Lori",
                "family": "Emerson",
                "sequence": "additional",
                "affiliation": []
            }
        ],
        "publisher": "Springer Science and Business Media LLC",
        "date": "2019-04-01T16:06:03Z",
        "keywords": [],
        "journal_title": "International Journal of Digital Humanities",
        "volume": "1",
        "issue": "1",
        "ISSN": [
            {
                "value": "2524-7832",
                "type": "print"
            },
            {
                "value": "2524-7840",
                "type": "electronic"
            }
        ]
    },
    {
        "url": "http://dx.doi.org/10.1007/s42803-019-00003-x",
        "identifier": {
            "string_id": "10.1007/s42803-019-00003-x",
            "id_scheme": "DOI"
        },
        "abstract": [],
        "article_title": "The .txtual condition, .txtual criticism and .txtual scholarly editing in Spanish philology",
        "authors": [
            {
                "ORCID": "http://orcid.org/0000-0002-9022-2699",
                "authenticated-orcid": false,
                "given": "Bénédicte",
                "family": "Vauthier",
                "sequence": "first",
                "affiliation": []
            }
        ],
        "publisher": "Springer Science and Business Media LLC",
        "date": "2019-03-05T06:50:54Z",
        "keywords": [],
        "journal_title": "International Journal of Digital Humanities",
        "volume": "1",
        "issue": "1",
        "ISSN": [
            {
                "value": "2524-7832",
                "type": "print"
            },
            {
                "value": "2524-7840",
                "type": "electronic"
            }
        ]
    },
    {
        "url": "http://dx.doi.org/10.1007/s42803-019-00002-y",
        "identifier": {
            "string_id": "10.1007/s42803-019-00002-y",
            "id_scheme": "DOI"
        },
        "abstract": [],
        "article_title": "From time theft to time stamps: mapping the development of digital forensics from law enforcement to archival authority",
        "authors": [
            {
                "given": "Corinne",
                "family": "Rogers",
                "sequence": "first",
                "affiliation": []
            }
        ],
        "publisher": "Springer Science and Business Media LLC",
        "date": "2019-03-04T14:23:12Z",
        "keywords": [],
        "journal_title": "International Journal of Digital Humanities",
        "volume": "1",
        "issue": "1",
        "ISSN": [
            {
                "value": "2524-7832",
                "type": "print"
            },
            {
                "value": "2524-7840",
                "type": "electronic"
            }
        ]
    },
    {
        "url": "http://dx.doi.org/10.1007/s42803-019-00011-x",
        "identifier": {
            "string_id": "10.1007/s42803-019-00011-x",
            "id_scheme": "DOI"
        },
        "abstract": [],
        "article_title": "Born-digital archives",
        "authors": [
            {
                "given": "Thorsten",
                "family": "Ries",
                "sequence": "first",
                "affiliation": []
            },
            {
                "given": "Gábor",
                "family": "Palkó",
                "sequence": "additional",
                "affiliation": []
            }
        ],
        "publisher": "Springer Science and Business Media LLC",
        "date": "2019-03-25T13:02:39Z",
        "keywords": [],
        "journal_title": "International Journal of Digital Humanities",
        "volume": "1",
        "issue": "1",
        "ISSN": [
            {
                "value": "2524-7832",
                "type": "print"
            },
            {
                "value": "2524-7840",
                "type": "electronic"
            }
        ]
    }
]